topsis/__init__.py
topsis/__main__.py
topsis_lovish_102117148-1.0.2.dist-info/METADATA
topsis_lovish_102117148-1.0.2.dist-info/WHEEL
topsis_lovish_102117148-1.0.2.dist-info/entry_points.txt
topsis_lovish_102117148-1.0.2.dist-info/top_level.txt
topsis_lovish_102117148-1.0.2.dist-info/RECORD
